Metadata-Version: 2.1
Name: dfupsert
Version: 0.0.3
Summary: "dfupsert" is a Python package for synchronizing pd.DataFrames with databases using seamless dfupsert (insert or update) operations.
Author: GuangJun Liang
Author-email: gaungjun_l@icloud.com
Keywords: python,pandas,sql,dfupsert,update,etl
Classifier: Development Status :: 3 - Alpha
Classifier: Intended Audience :: Developers
Classifier: Programming Language :: Python :: 3
Classifier: Operating System :: Unix
Classifier: Operating System :: MacOS :: MacOS X
Classifier: Operating System :: Microsoft :: Windows
Classifier: License :: OSI Approved :: MIT License
License-File: LICENSE
Requires-Dist: sqlalchemy
Requires-Dist: pandas
